main.py
hashpass-0.1.1.dist-info/LICENSE
hashpass-0.1.1.dist-info/WHEEL
hashpass-0.1.1.dist-info/METADATA
hashpass-0.1.1.dist-info/RECORD
