Metadata-Version: 2.1
Name: hashpass
Version: 0.1.1
Summary: 哈希密码生成程序
Home-page: https://github.com/guaifish/hashpass
License: MIT
Author: guaifish
Author-email: guaifish@foxmail.com
Requires-Python: >=3.8,<4.0
Classifier: License :: OSI Approved :: MIT License
Classifier: Programming Language :: Python :: 3
Classifier: Programming Language :: Python :: 3.8
Requires-Dist: gooey (>=1.0.3,<2.0.0)
Requires-Dist: pyinstaller (>=3.6,<4.0)
Requires-Dist: pyperclip (>=1.8.0,<2.0.0)
Project-URL: Repository, https://github.com/guaifish/hashpass
